{"data":{"allMarkdownRemark":{"totalCount":1,"edges":[{"node":{"fields":{"slug":"pricing/bảng-gia-quảng-cao-truyền-hinh-vtv-8-2019","date":"2019-01-03T17:00:00.000Z"},"excerpt":"Bảng Giá Quảng Cáo Truyền Hình VTV8 2018 Hải Nam  cung cấp bảng giá niêm yết đài truyền hình VTV8 năm 2018 Chính sách giảm giá quảng cáo…","timeToRead":1,"frontmatter":{"title":"Bảng Giá Quảng Cáo Truyền Hình VTV8 2019","tags":["Pricing truyền hình"],"cover":"/assets/pricing-vtv8.jpg","date":"2019-01-04T01:51:46.450Z"}}}]}},"pageContext":{"tag":"Pricing truyền hình"}}